ug_gpib/__init__.py
ug_gpib/_version.py
ug_gpib/gpib_helper.py
ug_gpib/ug_gpib.py
ug_gpib-1.2.2.dist-info/LICENSE
ug_gpib-1.2.2.dist-info/METADATA
ug_gpib-1.2.2.dist-info/WHEEL
ug_gpib-1.2.2.dist-info/top_level.txt
ug_gpib-1.2.2.dist-info/RECORD
