Metadata-Version: 2.1
Name: ug-gpib
Version: 1.2.2
Summary: A Python3 pyUSB library for the LQ Electronics Corp. UGPlus USB to GPIB Controller.
Author-email: Patrick Baus <patrick.baus@physik.tu-darmstadt.de>, Jacob Alexander <haata@kiibohd.com>
License: GNU General Public License v3 (GPLv3)
Project-URL: Homepage, https://github.com/PatrickBaus/pyUgGpib
Project-URL: Bug Tracker, https://github.com/PatrickBaus/pyUgGpib/issues
Project-URL: Download, https://github.com/PatrickBaus/pyUgGpib/releases
Keywords: UGPlus,GPIB,API
Classifier: Programming Language :: Python :: 3
Classifier: Programming Language :: Python :: 3.8
Classifier: Programming Language :: Python :: 3.9
Classifier: Programming Language :: Python :: 3.10
Classifier: Programming Language :: Python :: 3.11
Classifier: Development Status :: 5 - Production/Stable
Classifier: License :: OSI Approved :: GNU General Public License v3 (GPLv3)
Classifier: Operating System :: OS Independent
Classifier: Intended Audience :: Developers
Classifier: Intended Audience :: Science/Research
Classifier: Natural Language :: English
Classifier: Topic :: Home Automation
Classifier: Topic :: Scientific/Engineering
Requires-Python: >=3.7
License-File: LICENSE
Requires-Dist: pyusb ~=1.2.1
Requires-Dist: typing-extensions ; python_version < "3.11"
Provides-Extra: dev
Requires-Dist: black ; extra == 'dev'
Requires-Dist: build ; extra == 'dev'
Requires-Dist: isort ; extra == 'dev'
Requires-Dist: mypy ; extra == 'dev'
Requires-Dist: pre-commit ; extra == 'dev'
Requires-Dist: pylint ; extra == 'dev'
Requires-Dist: twine ; extra == 'dev'
Provides-Extra: test
Requires-Dist: mypy ; extra == 'test'
Requires-Dist: pylint ; extra == 'test'
Requires-Dist: setuptools ; extra == 'test'
